aracnid_core/__init__.py
aracnid_core/base.py
aracnid_core-0.1.3.dist-info/LICENSE
aracnid_core-0.1.3.dist-info/METADATA
aracnid_core-0.1.3.dist-info/WHEEL
aracnid_core-0.1.3.dist-info/RECORD
