Metadata-Version: 2.3
Name: aracnid-core
Version: 0.1.3
Summary: Base interfaces for Aracnid integration connectors
License: MIT
Keywords: abstract,connector
Author: Jason Romano
Author-email: aracnid@gmail.com
Requires-Python: >=3.10,<4.0
Classifier: License :: OSI Approved :: MIT License
Classifier: Programming Language :: Python :: 3
Classifier: Programming Language :: Python :: 3.10
Classifier: Programming Language :: Python :: 3.11
Classifier: Programming Language :: Python :: 3.12
Classifier: Programming Language :: Python :: 3.13
Project-URL: Repository, https://github.com/aracnid/aracnid-core
